{"follovving": "following", "tvvo": "two", "vvill": "will", "vvas": "was", "vvith": "with", "svould": "would", "svhat": "what", "svith": "with", "svhile": "while", "svaste": "waste", "tsvo": "two", "svhich": "which", "svorse": "worse", "midsvay": "midway", "osvn": "own", "svorld": "world", "svay": "way", "xvorks": "works", "xvould": "would", "xvell": "well", "xvere": "were", "xvhole": "whole", "oxves": "owes", "xvhich": "which", "xvithout": "without", "xvith": "with", "endoxved": "endowed", "laxv": "law", "xvork": "work", "xvealth": "wealth", "xvide": "wide", "xvill": "will", "broxv": "brow", "croxvn": "crown", "xvay": "way", "moclern": "modern", "aclvantages": "advantages", "cleclare": "declare", "clivert": "divert", "clivision": "division", "icleal": "ideal", "neecl": "need", "provicling": "providing", "inclividualized": "individualized", "procluction": "production", "clriven": "driven", "clebate": "debate", "clishes": "dishes", "aclapted": "adapted", "cletain": "detain", "cloes": "does", "tracles": "trades", "inclirectly": "indirectly", "outsicle": "outside", "acld": "add", "stuclies": "studies", "aclvance": "advance", "indiviclually": "individually", "cecled": "ceded", "alreacly": "already", "aclvantage": "advantage", "stucly": "study", "conclition": "condition", "clemand": "demand", "clemocracy": "democracy", "cliscourages": "discourages", "canclid": "candid", "macle": "made", "clate": "date", "eclucated": "educated", "sturcly": "sturdy", "sicle": "side", "attenclance": "attendance", "provicled": "provided", "clistress": "distress", "cliscover": "discover", "aclam": "adam", "attitucle": "attitude", "eviclently": "evidently", "cleveloped": "developed", "neecled": "needed", "clirection": "direction", "knowleclge": "knowledge", "stuclent": "student", "renclered": "rendered", "clead": "dead", "cleeper": "deeper", "clozen": "dozen", "corresponclence": "correspondence", "clelicate": "delicate", "everybocly": "everybody", "clifferent": "different", "clanger": "danger", "clirect": "direct", "clepartments": "departments", "provicle": "provide", "boarcls": "boards", "consiclers": "considers", "clevise": "devise", "aclapt": "adapt", "cloing": "doing", "tracle": "trade", "worcls": "words", "juclge": "judge", "servitucle": "servitude", "clirectly": "directly", "indiviclualism": "individualism", "hundrecls": "hundreds", "gracle": "grade", "remincled": "reminded", "aclequate": "adequate", "bicls": "bids", "moclels": "models", "aclded": "added", "meclical": "medical", "eclucation": "education", "clifficult": "difficult", "cluring": "during", "clesired": "desired", "uncler": "under", "conclitions": "conditions", "philaclelphia": "philadelphia", "ancl": "and", "clisregard": "disregard", "toclay": "today", "inclustrial": "industrial", "inclucles": "includes", "clesire": "desire", "aicls": "aids", "clesirable": "desirable", "cluty": "duty", "icleals": "ideals", "leacling": "leading", "iclea": "idea", "eviclence": "evidence", "aclams": "adams", "clestinies": "destinies", "wicle": "wide", "clegree": "degree", "sicles": "sides", "clifference": "difference", "climinished": "diminished", "clirected": "directed", "clistrict": "district", "icleas": "ideas", "lonclon": "london", "presiclent": "president", "bocly": "body", "clid": "did", "clevelopment": "development", "towarcls": "towards", "meclicine": "medicine", "methocls": "methods", "orcler": "order", "clrafted": "drafted", "aucliting": "auditing", "aclvocacy": "advocacy", "chilclren": "children", "unclertake": "undertake", "neecls": "needs", "cclll": "call", "idecll": "ideal", "cllarmed": "alarmed", "cclse": "case", "hcld": "had", "hclve": "have", "lllost": "most", "elelllents": "elements", "perlllit": "permit", "econollly": "economy", "enorlllous": "enormous", "inclelllent": "inclement", "edlllund": "edmund", "lllean": "mean", "lilllit": "limit", "alll": "am", "suprellle": "supreme", "seellls": "seems", "llle": "me", "overwhelllling": "overwhelming", "llloclern": "modern", "lllan": "man", "accolllpanied": "accompanied", "forllled": "formed", "illlperative": "imperative", "silllilarly": "similarly", "solllething": "something", "lllunicipal": "municipal", "aillls": "aims", "fallliliar": "familiar", "lllode": "mode", "governlllent": "government", "rallls": "rams", "stateslllan": "statesman", "lllethods": "methods", "adlllinistration": "administration", "perforlll": "perform", "lllind": "mind", "lllodern": "modern", "colllfortable": "comfortable", "colllpromise": "compromise", "becollles": "becomes", "dynalllic": "dynamic", "colllplex": "complex", "elllploy": "employ", "farlller": "farmer", "clailll": "claim", "lllember": "member", "lllaking": "making", "agreelllents": "agreements", "rollle": "rome", "dellland": "demand", "meantillle": "meantime", "llloreover": "moreover", "favoritislll": "favoritism", "llly": "my", "intilllately": "intimately", "farlll": "farm", "lilllited": "limited", "attelllpt": "attempt", "sometillles": "sometimes", "collles": "comes", "lllake": "make", "lllysteries": "mysteries", "outcollle": "outcome", "tillle": "time", "movelllent": "movement", "eolllmereial": "eommereial", "colllmands": "commands", "jallles": "james", "verlllont": "vermont", "firlll": "firm", "llleaning": "meaning", "criticislll": "criticism", "illlportant": "important", "arllled": "armed", "silllply": "simply", "lllakes": "makes", "lllerely": "merely", "alllong": "among", "hilll": "him", "illlmediately": "immediately", "llliss": "miss", "lilllits": "limits", "colllpleted": "completed", "sallle": "same", "reforlller": "reformer", "lllall": "mall", "assulllption": "assumption", "lllotto": "motto", "llloderll": "moderll", "collle": "come", "lllatter": "matter", "colllplexity": "complexity", "lllass": "mass", "forlllation": "formation", "melllbers": "members", "menlbers": "members", "tinle": "time", "inlplies": "implies", "conlparisons": "comparisons", "fronl": "from", "nlove": "move", "firnl": "firm", "conle": "come", "comnlercial": "commercial", "nlally": "mally", "departnlents": "departments", "anlong": "among", "nlember": "member", "systenl": "system", "nlany": "many", "nlake": "make", "econonlics": "economics", "inlpossible": "impossible", "nlealls": "mealls", "nlay": "may", "nlost": "most", "nlen": "men", "sanle": "same", "exanline": "examine", "clepartnlents": "departments", "colunlbia": "columbia", "nlust": "must", "problenls": "problems", "willianl": "william", "sometinles": "sometimes", "thenl": "them", "deenl": "deem", "seenled": "seemed", "beconle": "become", "sinlilar": "similar", "comnlerce": "commerce", "nlore": "more", "developnlent": "development", "wonlen": "women", "conlpetition": "competition", "lltlnlall": "lltlmall", "lnllst": "lmlst", "conlmerce": "commerce", "anlollg": "amollg", "illodern": "modern", "illall": "mall", "illake": "make", "farill": "farm", "deilland": "demand", "illaterial": "material", "illay": "may", "scheilles": "schemes", "eilliglltened": "emiglltened", "illorality": "morality", "reilledy": "remedy", "oilly": "omy", "perillitted": "permitted", "illost": "most", "bottoill": "bottom", "illethods": "methods", "rnen": "men", "tirne": "time", "sirnply": "simply", "rnost": "most", "rnell": "mell", "problern": "problem", "rnore": "more", "lirnited": "limited", "ernployer": "employer", "systerns": "systems", "rnatter": "matter", "cornpetition": "competition", "ternporary": "temporary", "frorn": "from", "cornfort": "comfort", "arnerican": "american", "rnedicine": "medicine", "criticisrn": "criticism", "corne": "come", "freecloln": "freeclom", "clailned": "claimed", "llilnself": "llimself", "nulnerous": "numerous", "falniliar": "familiar", "telnporary": "temporary", "econolnic": "economic", "adaln": "adam", "argulnent": "argument", "ilnmediate": "immediate", "departlnents": "departments", "developlnellt": "developmellt", "colnplex": "complex", "lnarket": "market", "lnealls": "mealls", "lilnitations": "limitations", "outcolne": "outcome", "relnain": "remain", "nolninally": "nominally", "econolnics": "economics", "theln": "them", "warln": "warm", "estilnate": "estimate", "adlnitting": "admitting", "lnell": "mell", "colnplexity": "complexity", "collnected": "colmected", "extrelne": "extreme", "lnacle": "made", "hilnself": "himself", "alnollg": "amollg", "lnean": "mean", "gerlnan": "german", "solnething": "something", "nulnber": "number", "lnonarchs": "monarchs", "solne": "some", "becalne": "became", "lnake": "make", "perlnanently": "permanently", "lnention": "mention", "froln": "from", "colnmercial": "commercial", "curricululn": "curriculum", "lnost": "most", "eomlnereial": "eommereial", "coln": "com", "colnmon": "common", "silnple": "simple", "silnilar": "similar", "lnunicipality": "municipality", "ilnpossible": "impossible", "alnong": "among", "schelne": "scheme", "legitilnate": "legitimate", "nationalisln": "nationalism", "telnptation": "temptation", "lnind": "mind", "nalnely": "namely", "lnoral": "moral", "adlnit": "admit", "tilnes": "times", "lnany": "many", "seelned": "seemed", "tilnid": "timid", "passlng": "passmg", "colnlnercial": "commercial", "lnutual": "mutual", "hiln": "him", "adlnission": "admission", "profollnd": "profolmd", "lnakes": "makes", "systeln": "system", "comlnunity": "community", "elnploying": "employing", "llniversities": "lmiversities", "tilne": "time", "incolnpatible": "incompatible", "treatlnent": "treatment", "lnove": "move", "imperialisln": "imperialism", "inforlnation": "information", "environlnent": "environment", "forln": "form", "salne": "same", "forlned": "formed", "lnen": "men", "lnastery": "mastery", "colnpetitive": "competitive", "governlnent": "government", "econolny": "economy", "colnposed": "composed", "eolnpetition": "eompetition", "lnade": "made", "becolne": "become", "follnd": "folmd", "adlnitted": "admitted", "hulnanity": "humanity", "silnply": "simply", "lnust": "must", "thelnselves": "themselves", "lnan": "man", "lnatter": "matter", "comlnunities": "communities", "exalnination": "examination", "lnally": "mally", "comlnerce": "commerce", "lnodern": "modern", "perlnanent": "permanent", "lilnited": "limited", "eomlnercial": "eommercial", "lnental": "mental", "probleln": "problem", "lnall": "mall", "parlialnents": "parliaments", "lnore": "more", "colnpetition": "competition", "lnayor": "mayor", "materialisln": "materialism", "seelns": "seems", "departlnent": "department", "lnarked": "marked", "alnerican": "american", "elnployment": "employment", "lnasterpiece": "masterpiece", "folln": "folm", "alnos": "amos", "lnay": "may", "sometilnes": "sometimes", "elelnent": "element", "gerlnany": "germany", "circuznstances": "circumstances", "coznpetitors": "competitors", "adazn": "adam", "znembers": "members", "znind": "mind", "coznlllercial": "comlllercial", "frozn": "from", "coznmercial": "commercial", "econoznic": "economic", "sozne": "some", "soznewhat": "somewhat", "coznpetitive": "competitive", "fleeclozn": "fleeclom", "eoznpromise": "eompromise", "coznpetition": "competition", "statenzent": "statement", "nzodern": "modern", "nzay": "may", "conzpete": "compete", "elenzent": "element", "ronze": "rome", "ulaterials": "materials", "auleriean": "ameriean", "adulit": "admit", "coulonercial": "comonercial", "sllould": "sllomd", "coulmunity": "community", "ulonographs": "monographs", "coulpletion": "completion", "srould": "sromd", "uleaning": "meaning", "gaule": "game", "eoulltries": "eomltries", "foulld": "fomld", "coulpetition": "competition", "fullctioll": "fmlctioll", "perulitted": "permitted", "exaulple": "example", "ulould": "mould", "foruler": "former", "sulall": "small", "ulay": "may", "uleeting": "meeting", "ulen": "men", "becoules": "becomes", "anatouly": "anatomy", "freecloul": "freeclom", "comulerce": "commerce", "comulercial": "commercial", "ulore": "more", "teruled": "termed", "developulent": "development", "parliaulent": "parliament", "suldjects": "smdjects", "ulake": "make", "froul": "from", "ulliversities": "mliversities", "ulutual": "mutual", "colulnercial": "colmnercial", "ulade": "made", "ulodify": "modify", "coule": "come", "reforul": "reform", "saule": "same", "uloclern": "modern", "feudalisul": "feudalism", "regulatioll": "regmatioll", "forul": "form", "soule": "some", "freedoul": "freedom", "econotnics": "economics", "etnpires": "empires", "minitnize": "minimize", "retnoval": "removal", "assutned": "assumed", "jatnes": "james", "aitns": "aims", "refortner": "reformer", "individualistn": "individualism", "attaintnent": "attainment", "phenotnena": "phenomena", "cotne": "come", "frotn": "from", "titnes": "times", "thetnselves": "themselves", "tnodern": "modern", "tnent": "ment", "tnealls": "mealls", "tnay": "may", "firtn": "firm", "litnit": "limit", "hetnisphere": "hemisphere", "cotnpromise": "compromise", "adjusttnent": "adjustment", "satne": "same", "stnitlls": "smitlls", "tnatter": "matter", "tnaking": "making", "sitnple": "simple", "titne": "time", "fortn": "form", "investtnents": "investments", "econotnic": "economic", "tnust": "must", "tnany": "many", "governtnent": "government", "cotning": "coming", "comtnunity": "community", "thetn": "them", "schetne": "scheme", "cotnmunity": "community", "anitnal": "animal", "itnmediately": "immediately", "realtn": "realm", "econotny": "economy", "tnanifesting": "manifesting", "cotnmencement": "commencement", "tnerely": "merely", "pritnitive": "primitive", "tnore": "more", "tnen": "men", "judgtnent": "judgment", "cotnparatively": "comparatively", "fartn": "farm", "attnosphere": "atmosphere", "sotne": "some", "tnental": "mental", "seetns": "seems", "tnell": "mell", "freedotn": "freedom", "tnacle": "made", "atnerican": "american", "probletn": "problem", "claitned": "claimed", "tnoclern": "modern", "septetnber": "september", "patriotistn": "patriotism", "hartnony": "harmony", "tnost": "most", "lnaximutn": "lnaximum", "cotnlllercial": "comlllercial", "regitne": "regime", "tnan": "man", "cotnpetition": "competition", "refortn": "reform", "anitnals": "animals", "comtnon": "common", "interestilag": "mterestilag", "criine": "crime", "inountains": "mountains", "statesinall": "statesmall", "btlsiness": "btlsmess", "inan": "man", "eertain": "eertam", "inall": "mall", "notlling": "notllmg", "fainiliar": "familiar", "sometiines": "sometimes", "witllin": "witllm", "inuch": "much", "ineqllality": "meqllality", "socialisin": "socialism", "deterinine": "determine", "trailling": "traillmg", "coinpel": "compel", "doetrine": "doetrme", "fillding": "filldmg", "curriculuin": "curriculum", "indllstry": "mdllstry", "instructioll": "mstructioll", "developinellt": "developmellt", "inoderll": "moderll", "illcreasingly": "illcreasmgly", "idcal": "ideal", "conc": "cone", "eolnmercial": "eolnmereial", "ecollomic": "ecollomie", "colllmuolity": "eolllmuolity", "edtlcation": "edtleation", "comllloll": "eomllloll", "commoll": "eommoll", "rcsult": "result", "tlzeir": "their", "tlzat": "that", "tlze": "the", "wlzose": "whose", "nomilzally": "nominally", "prilzciple": "principle", "gelzerally": "generally", "alolzg": "along", "lzlally": "mally", "ilzterests": "interests", "natiolzs": "nations", "investigatilzg": "investigating", "filzd": "find", "gelzeral": "general", "existilzg": "existing", "alzd": "and", "olze": "one", "lzecessary": "necessary", "wrolzg": "wrong", "slaows": "snows", "cloilag": "doing", "apparelatly": "apparently", "uladue": "undue", "represelat": "represent", "employilag": "employing", "colatracts": "contracts", "italiala": "italian", "thala": "than", "conclitiolas": "conditions", "beilag": "being", "tilat": "tint", "correctilag": "correcting", "beela": "been", "judgmelat": "judgment", "alacestry": "ancestry", "hulager": "hunger", "progelay": "progeny", "growilag": "growing", "laeeded": "needed", "extelat": "extent", "colaclitions": "conditions", "sectiolas": "sections", "nilaeteen": "nineteen", "fitlaess": "fitness", "alad": "and", "sollae": "some", "tenlaessee": "tennessee", "evolutiola": "evolution", "ecolaomic": "economic", "intelasive": "intensive", "opiniolas": "opinions", "filad": "find", "laave": "nave", "distributiola": "distribution", "speculatiola": "speculation", "olae": "one", "foulad": "found", "differelat": "different", "laeither": "neither", "sessiolas": "sessions", "alolae": "alone", "frequelat": "frequent", "betweela": "between", "dalager": "danger", "statilag": "stating", "ulader": "under", "learnilag": "learning", "anarclay": "anarchy", "wlao": "who", "laas": "has", "tlais": "this", "tlaat": "that", "laaving": "having", "whicla": "which", "tlae": "the", "lais": "his", "laand": "hand", "twentietla": "twentieth", "tlaese": "these", "wlaich": "which", "tlaeir": "their", "tlaeory": "theory", "otiler": "other", "iilterests": "ihterests", "englisil": "english", "silow": "show", "tilis": "this", "ilis": "his", "witil": "with", "colilpetitioll": "colhpetitioll", "higiler": "higher", "ilave": "have", "faitil": "faith", "silall": "shall", "aild": "ahd", "ilas": "has", "wilich": "which", "tilese": "these", "tilousands": "thousands", "trutlls": "truths", "xvitll": "with", "establislles": "establishes", "ligllt": "light", "sopllomore": "sophomore", "riglltly": "rightly", "soutll": "south", "tlleir": "their", "sllop": "shop", "tlleoretical": "theoretical", "llire": "hire", "llamlet": "hamlet", "forefatllers": "forefathers", "cllildren": "children", "tecllllieal": "techllieal", "llaving": "having", "cllarles": "charles", "otller": "other", "llere": "here", "insigllt": "insight", "eartll": "earth", "llell": "hell", "eeollomie": "eeohomie", "sllip": "ship", "tlleft": "theft", "neigllbors": "neighbors", "autlloritative": "authoritative", "alollg": "alohg", "sllut": "shut", "altllough": "although", "llis": "his", "lleld": "held", "alld": "ahd", "alnericall": "alnericah", "wllo": "who", "tootll": "tooth", "rutllless": "ruthless", "strengtll": "strength", "tllere": "there", "llistorical": "historical", "stretclles": "stretches", "tllemselves": "themselves", "departlllellts": "departlllehts", "worsllip": "worship", "sllops": "shops", "llope": "hope", "llence": "hence", "brotller": "brother", "cllance": "chance", "trutll": "truth", "trlle": "trhe", "fatller": "father", "sllow": "show", "weigll": "weigh", "tllousand": "thousand", "llealing": "healing", "frotll": "froth", "wlly": "why", "lllally": "hlally", "llorse": "horse", "llad": "had", "cllaracters": "characters", "diminisll": "diminish", "botll": "both", "thell": "theh", "orgallization": "orgahization", "waslling": "washing", "clloose": "choose", "sllape": "shape", "tllat": "that", "restrictiolls": "restrictiohs", "llowever": "however", "llold": "hold", "llighly": "highly", "lligh": "high", "agellts": "agehts", "tecllnically": "technically", "tllell": "theh", "eall": "eah", "teaclling": "teaching", "sclleme": "scheme", "allead": "ahead", "traillillg": "traihillg", "wortll": "worth", "solnetlling": "something", "furnislling": "furnishing", "gllastly": "ghastly", "pllysical": "physical", "psycllology": "psychology", "eigllteenth": "eighteenth", "tlley": "they", "wllat": "what", "thorougllly": "thoroughly", "twentietll": "twentieth", "tllese": "these", "slaugllter": "slaughter", "higller": "higher", "englisll": "english", "wllell": "whell", "etllics": "ethics", "latller": "lather", "xvealtll": "wealth", "tllreats": "threats", "acllievement": "achievement", "matllematics": "mathematics", "slle": "she", "ller": "her", "witll": "with", "thougllts": "thoughts", "svllile": "while", "breadtll": "breadth", "livelillood": "livelihood", "tllrough": "through", "splleres": "spheres", "llave": "have", "scllool": "school", "llot": "hot", "tllose": "those", "frencll": "french", "llpoll": "llpoh", "healtlly": "healthy", "tllis": "this", "otllerwise": "otherwise", "sllort": "short", "lland": "hand", "llelp": "help", "lleredity": "heredity", "rapllael": "raphael", "sllell": "shell", "llall": "hall", "llecessary": "hecessary", "pllysiology": "physiology", "ballkillg": "ballkihg", "whiell": "whieh", "sllowed": "showed", "sympatlly": "sympathy", "annillilation": "annihilation", "alllollg": "alllohg", "tllall": "thall", "olll": "olh", "lllllst": "hlllst", "wllile": "while", "llospital": "hospital", "metllods": "methods", "whetller": "whether", "bellalf": "behalf", "wllose": "whose", "perllaps": "perhaps", "bellind": "behind", "tlle": "the", "wllatever": "whatever", "wllolly": "wholly", "wllicll": "whicll", "abolisll": "abolish", "tllou": "thou", "llard": "hard", "reaclled": "reached", "prollibit": "prohibit", "llas": "has", "llasten": "hasten", "llarmonious": "harmonious", "cllildrell": "childrell", "searcll": "search", "svllich": "which", "wislled": "wished", "utall": "utah", "rigllt": "right", "tllt": "tht", "tlleln": "them", "wllereby": "whereby", "everytlling": "everything", "liglltly": "lightly", "lliln": "him", "metllocls": "methods", "exllaustive": "exhaustive", "connectioll": "connectioh", "althougll": "although", "selfisllness": "selfishness", "tlleories": "theories", "llow": "how", "rigllts": "rights", "higllly": "highly", "sucll": "such", "growtll": "growth", "ratller": "rather", "tllread": "thread", "filld": "fihd", "patcllwork": "patchwork", "lleed": "heed", "llumber": "humber", "lllln": "llhn", "llletllods": "methods", "tllem": "them", "wlaicll": "which", "inllabit": "inhabit", "nevertlleless": "nevertheless", "prollibits": "prohibits", "lligller": "higher", "llatural": "hatural", "establislled": "established", "sougllt": "sought", "otlr": "ohr", "wotlld": "wohld", "btlsilless": "bhsilless", "trtle": "trhe", "partictllar": "partichlar", "ttle": "the", "tllal": "hlal", "ttlrotlgll": "throtlgll", "cetltllry": "cehtllry", "productiotl": "productioh", "otle": "ohe", "otlly": "ohly", "itlterests": "ihterests", "yotl": "yoh", "cotltract": "cohtract", "throtlgh": "throhgh", "jtlstice": "jhstice", "itlstitlltioll": "ihstitlltioll", "partietllar": "partiehlar", "tlpon": "hpon", "declaratiotl": "declaratioh", "thtls": "thhs", "tllilld": "hlilld", "movemetlt": "movemeht", "treatmetlt": "treatmeht", "catl": "cah", "providitlg": "providihg", "mtlst": "mhst", "qtlalify": "qhalify", "ptlblic": "phblic", "otlt": "oht", "ptlrpose": "phrpose", "whictl": "which", "colupetitiotl": "colupetitioh", "grotlp": "grohp", "trallspoltatiotl": "trallspoltatioh", "stleet": "sheet", "agreetllellt": "agreehlellt", "stlcll": "shcll", "llpotl": "llpoh", "wtlicll": "whicll", "atld": "ahd", "cotlceived": "cohceived", "consequetltly": "consequehtly", "operatiotl": "operatioh", "centtlry": "centhry", "btlt": "bht", "llatld": "llahd", "withotlt": "withoht", "ecollotllic": "ecollohlic", "utlcler": "uhcler", "itldustria": "ihdustria", "otlght": "ohght", "tlot": "hot", "extetlt": "exteht", "restitlg": "restihg", "jtlst": "jhst", "lneatls": "lneahs", "givillg": "giving", "ulldertake": "undertake", "uncollsciously": "unconsciously", "paillless": "painless", "selld": "send", "dissellt": "dissent", "orgallizatioll": "orgahization", "sanitatioll": "sanitation", "conflictillg": "conflicting", "origillate": "originate", "comtnullity": "community", "evidellt": "evident", "colltinually": "continually", "lleecls": "needs", "illdustrial": "industrial", "propositioll": "proposition", "ellter": "enter", "everincreasillg": "everincreasing", "distillctions": "distinctions", "parliamelltary": "parliamentary", "illdllstry": "mdllstry", "witllill": "witllm", "extensioll": "extension", "milld": "mind", "cincinllati": "cincinnati", "demalld": "demand", "balallce": "balance", "leadillg": "leading", "productioll": "production", "givell": "given", "persollal": "personal", "kllowledge": "knowledge", "johll": "john", "passillg": "passing", "inclillation": "inclination", "observatioll": "observation", "convictioll": "conviction", "wastillg": "wasting", "illterpreter": "interpreter", "lltllllall": "lltlmall", "lookillg": "looking", "engilleer": "engineer", "editioll": "edition", "londoll": "london", "persolls": "persons", "settillg": "setting", "ascendillg": "ascending", "ecollolny": "economy", "ollly": "only", "advallced": "advanced", "appearallce": "appearance", "ecolloznic": "economic", "questioll": "question", "illsists": "insists", "valls": "vans", "developlllellt": "developmellt", "frellch": "french", "collsists": "consists", "prevellts": "prevents", "llulnber": "number", "coznpetitioll": "competition", "explaills": "explains", "ollward": "onward", "strellgth": "strength", "illcrease": "increase", "collsiderations": "considerations", "sellse": "sense", "represellt": "represent", "installces": "instances", "hellry": "henry", "reasollable": "reasonable", "moclerll": "modern", "differellt": "different", "seeillg": "seeing", "eurrieululll": "eurrieululn", "llilllself": "llimself", "recogllition": "recognition", "llothing": "nothing", "crimillal": "criminal", "illdefinitely": "indefinitely", "solls": "sons", "illtellect": "intellect", "expellses": "expenses", "examille": "examine", "illcreasillgly": "illcreasmgly", "treatmellt": "treatment", "illterestilag": "mterestilag", "turll": "turn", "eompetitioll": "eompetition", "cloillg": "doing", "recognitioll": "recognition", "illdependent": "independent", "residellt": "resident", "woll": "won", "enlightelled": "enlightened", "weapolls": "weapons", "illstitution": "institution", "lalld": "land", "illcreases": "increases", "savillgs": "savings", "exceptiollal": "exceptional", "reputatioll": "reputation", "eclucatioll": "education", "restrictillg": "restricting", "followillg": "following", "collduct": "conduct", "beyolld": "beyond", "learlled": "learned", "determilles": "determines", "coverillg": "covering", "additioll": "addition", "strellgthened": "strengthened", "irritatioll": "irritation", "educatiollal": "educational", "understallds": "understands", "eolllpetition": "eompetition", "detnallds": "detnands", "utopiall": "utopian", "formatioll": "formation", "plalle": "plane", "managemellt": "management", "plalles": "planes", "bargaill": "bargain", "retailled": "retained", "lloble": "noble", "expressioll": "expression", "embracillg": "embracing", "underlyillg": "underlying", "elljoy": "enjoy", "folllld": "folmd", "medicille": "medicine", "appropriatioll": "appropriation", "puritall": "puritan", "argumellt": "argument", "oftell": "often", "defillite": "definite", "groullds": "grounds", "fallell": "fallen", "fitlless": "fitness", "confrollted": "confronted", "llalld": "hand", "illstitute": "institute", "agaillst": "against", "pretellds": "pretends", "illtense": "intense", "conditioll": "condition", "appellded": "appended", "achievemellts": "achievements", "destilled": "destined", "borlle": "borne", "sometllillg": "sometlling", "collception": "conception", "mallifests": "manifests", "referellce": "reference", "thillk": "think", "telln": "tenn", "illforlnation": "information", "llor": "nor", "illstitutioll": "institution", "pennsylvallia": "pennsylvania", "ullknown": "unknown", "alltwerp": "antwerp", "orgallizing": "organizing", "ullcertain": "uncertain", "stalldard": "standard", "illstances": "instances", "upoll": "upon", "pellalty": "penalty", "regulatillg": "regulating", "generatioll": "generation", "expositioll": "exposition", "lastillg": "lasting", "jullior": "junior", "lllell": "mell", "showll": "shown", "dallger": "danger", "movemellt": "movement", "lilles": "lines", "collcede": "concede", "generatiolls": "generations", "rallge": "range", "ellgage": "engage", "illterchange": "interchange", "weaklless": "weakness", "politicialls": "politicians", "clifferellt": "different", "permissioll": "permission", "twellty": "twenty", "selectillg": "selecting", "collsistently": "consistently", "placillg": "placing", "belollgs": "belongs", "llation": "nation", "melltiolled": "melltioned", "centenllial": "centennial", "colltrolled": "controlled", "ellgaged": "engaged", "teell": "teen", "illstruction": "instruction", "collcrete": "concrete", "pursuillg": "pursuing", "tellt": "tent", "illstructioll": "mstructioll", "bitterlless": "bitterness", "illterlude": "interlude", "potellt": "potent", "illlportallt": "important", "attelldance": "attendance", "llominally": "nominally", "lollclon": "london", "hallds": "hands", "intervelltion": "intervention", "poillt": "point", "includillg": "including", "sarill": "sarin", "combinatiolls": "combinations", "nothillg": "nothing", "directioll": "direction", "dyllamic": "dynamic", "follll": "folm", "llotice": "notice", "developillg": "developing", "depellds": "depends", "lllealls": "mealls", "anciellt": "ancient", "bargaills": "bargains", "avoidillg": "avoiding", "fillance": "finance", "evokillg": "evoking", "presellt": "present", "detrimellt": "detriment", "busilless": "business", "cellttlry": "centhry", "remaill": "remain", "constitutiollal": "constitutional", "enjoyillg": "enjoying", "sooll": "soon", "goverlllllent": "government", "apprehelld": "apprehend", "departmellts": "departments", "utterallce": "utterance", "meallwhile": "meanwhile", "greells": "greens", "partisall": "partisan", "depelld": "depend", "collsequently": "consequently", "holdillg": "holding", "collditiolls": "conditiolls", "fulldamental": "fundamental", "prillciples": "principles", "lleeds": "needs", "ullravel": "unravel", "talkillg": "talking", "collgressional": "congressional", "alolle": "alone", "elevatiolls": "elevations", "corporatiolls": "corporations", "restillg": "resting", "hollored": "honored", "colll": "com", "eminellt": "eminent", "emergellce": "emergence", "harmolly": "harmony", "commissioll": "commission", "colltest": "contest", "colltrol": "control", "lnailltellallce": "lnailltellance", "visiollary": "visionary", "illequality": "inequality", "outlilled": "outlined", "collclition": "condition", "trallsaction": "transaction", "beginllillg": "beginnillg", "collsciously": "consciously", "illdebtedness": "indebtedness", "collvictioll": "conviction", "efficielltly": "efficiently", "borll": "born", "defilles": "defines", "filldillg": "filldmg", "preparillg": "preparing", "providillg": "providing", "trelld": "trend", "dozell": "dozen", "preparatioll": "preparation", "jacobsell": "jacobsen", "finallce": "finance", "combillations": "combinations", "billd": "bind", "sillce": "since", "elltered": "entered", "wiscollsin": "wisconsin", "mailltained": "maintained", "ellable": "enable", "accumulatillg": "accumulating", "thetllselves": "themselves", "llleall": "mean", "allcl": "and", "elljoying": "enjoying", "adlnissioll": "admission", "seell": "seen", "illtellectual": "intellectual", "nallce": "nance", "concerllillg": "concernillg", "wisconsill": "wisconsin", "accompallied": "accompanied", "ballkers": "bankers", "doetrille": "doetrme", "ordillary": "ordinary", "elltering": "entering", "illcludes": "includes", "cellters": "centers", "lollg": "long", "positiolls": "positions", "killgs": "kings", "religioll": "religion", "techllical": "technical", "poillts": "points", "boullded": "bounded", "callillg": "calling", "colllmissiollers": "conlmissiollers", "ratiollal": "rational", "currellt": "current", "penllsylvallia": "pennsylvania", "esselltially": "essentially", "contellt": "content", "governillg": "governing", "owller": "owner", "livillg": "living", "illeqllality": "meqllality", "rllen": "men", "profolllld": "profolmd", "attelltion": "attention", "ignorallce": "ignorance", "lllliversities": "lmiversities", "eontentiolls": "eontentions", "ecollomists": "economists", "provisioll": "provision", "collsequelltly": "consequently", "ellds": "ends", "federatioll": "federation", "llearly": "nearly", "incidellt": "incident", "parliamellt": "parliament", "ullderlyillg": "underlying", "colltrary": "contrary", "growll": "grown", "origill": "origin", "freeclolll": "freeclom", "tearillg": "tearing", "decisioll": "decision", "consequelltly": "consequently", "experimentatioll": "experimentation", "parellt": "parent", "behilld": "behind", "judgmellt": "judgment", "allarchy": "anarchy", "rallks": "ranks", "benllett": "bennett", "prevellted": "prevented", "prevellt": "prevent", "deville": "devine", "differelltiate": "differentiate", "fullctions": "functions", "willdy": "windy", "evellts": "events", "commollwealth": "commonwealth", "fractiollal": "fractional", "selectioll": "selection", "trustillg": "trusting", "indepelldent": "independent", "notllillg": "notllmg", "revealillg": "revealing", "writtell": "written", "competitioll": "competition", "workillg": "working", "paills": "pains", "collscious": "conscious", "ullto": "unto", "lleecled": "needed", "nineteellth": "nineteenth", "professioll": "profession", "extellt": "extent", "scielltific": "scientific", "pregllant": "pregnant", "patiellts": "patients", "persoll": "person", "eertaill": "eertam", "overtakell": "overtaken", "associatioll": "association", "foulldation": "foundation", "proviclillg": "providing", "combilled": "combined", "sentimellt": "sentiment", "recogllitioll": "recognition", "freedotll": "freedom", "illitiative": "initiative", "llight": "night", "restrictioll": "restriction", "recellt": "recent", "admillistration": "administration", "orgallic": "organic", "spelld": "spend", "attailled": "attained", "intellsively": "intensively", "demallds": "demands", "alltiquity": "antiquity", "cornerstolle": "cornerstone", "problerll": "problem", "departmellt": "department", "ruilled": "ruined", "illterest": "interest", "strengthenillg": "strengthening", "reasolls": "reasons", "illustratioll": "illustration", "dependellce": "dependence", "mailltain": "maintain", "beillgs": "beings", "pellnsylvallia": "pennsylvania", "apparellt": "apparent", "warpillg": "warping", "ullfavorable": "unfavorable", "illsurance": "insurance", "ulllimited": "unlimited", "illstitutional": "institutional", "collceived": "conceived", "reasoll": "reason", "delusioll": "delusion", "gralld": "grand", "plall": "plan", "conclitiolls": "conditions", "expellse": "expense", "portioll": "portion", "translatioll": "translation", "directiolls": "directions", "elllarge": "enlarge", "conclusiolls": "conclusions", "lllilld": "mind", "discrimillation": "discrimination", "ollce": "once", "subsistellce": "subsistence", "fullction": "function", "eanllot": "eannot", "thetll": "them", "absorbillg": "absorbing", "deprivillg": "depriving", "stalld": "stand", "illfected": "infected", "collllected": "colmected", "absellce": "absence", "irrigatioll": "irrigation", "apparelltly": "apparently", "witllessed": "witnessed", "ullcler": "under", "sessioll": "session", "llatures": "natures", "trallsportation": "transportation", "ullited": "united", "esselltial": "essential", "lyillg": "lying", "llational": "national", "admissioll": "admission", "adoptioll": "adoption", "citizells": "citizens", "illevitably": "inevitably", "eomlllereial": "eommereial", "collflicting": "conflicting", "elltrusted": "entrusted", "expressillg": "expressing", "llotlling": "notllmg", "illdividual": "individual", "ellabled": "enabled", "humall": "human", "presentillg": "presenting", "contractillg": "contracting", "operatioll": "operation", "exterlsive": "extensive", "rlatural": "natural", "limitatiorls": "limitations", "coznpetitiorl": "competition", "relatiorl": "relation", "lrlore": "more", "offerirlg": "offering", "derlying": "denying", "everl": "even", "orle": "one", "colrlpetitive": "competitive", "probletrl": "problem", "selectiorl": "selection", "irlclependellce": "inclependellce", "takirlg": "taking", "existeilce": "existence", "coilsequence": "consequence", "coiltract": "contract", "eighteeilth": "eighteenth", "theil": "then", "qualificatioils": "qualifications", "ilatural": "natural", "connectioil": "connection", "ecoilolnic": "economic", "natioilality": "nationality", "allloilg": "among", "professioilal": "professional", "ceilt": "cent", "expectiilg": "expecting", "alnericail": "american", "contiilues": "continues", "inteilded": "intended", "orgailization": "organization", "uiliversity": "university", "recogilize": "recognize", "intentioil": "intention", "ageilts": "agents", "ecoilomic": "economic", "cryiilg": "crying", "commoil": "common", "restrictioils": "restrictions", "cail": "can", "trainiilg": "training", "declaratioil": "declaration", "betweetl": "between", "regulatiotls": "regulations", "tyratlny": "tyranny", "doitlg": "doing", "listetl": "listen", "atlything": "anything", "thatl": "than", "positiotl": "position", "ttlost": "most", "gaitl": "gain", "ttlust": "must", "letld": "lend", "applyitlg": "applying", "developmetlt": "development", "lllatl": "man", "dowtl": "down", "descriptiotl": "description", "litle": "line", "precisiotl": "precision", "harnessitlg": "harnessing", "legislatiotl": "legislation", "actiotl": "action", "hatld": "hand", "advatltage": "advantage", "itldeed": "indeed", "metl": "men", "beetl": "been", "benevoletlce": "benevolence", "presetlted": "presented", "conditiotls": "conditions", "mitlers": "miners", "cantlot": "cannot", "evetl": "even", "boutlties": "bounties", "fratlkly": "frankly", "possessiotl": "possession", "presetltation": "presentation", "duritlg": "during", "letlt": "lent", "interestitlg": "interesting", "taketl": "taken", "etlglish": "english", "itlvolved": "involved", "lnetl": "men", "cotls": "cons", "metltal": "mental", "atly": "any", "itlstance": "instance", "concernitlg": "concerning", "meatl": "mean", "atlybody": "anybody", "utlfortunately": "unfortunately", "presidetlt": "president", "subsequetlt": "subsequent", "cotltributes": "contributes", "tlecessity": "necessity", "experietlce": "experience", "tlse": "use", "slatlghter": "slaughter", "dangerotls": "dangerous", "instittltion": "institution", "acttlal": "actual", "purstlit": "pursuit", "seriotls": "serious", "ftlture": "future", "capttlre": "capture", "ecltleation": "eclueation", "cotlrse": "course", "cotlntries": "countries", "individtlal": "individual", "ftllfillment": "fulfillment", "pleastlre": "pleasure", "grotlnd": "ground", "eqtlality": "equality", "qtlite": "quite", "tlnfit": "unfit", "otltside": "outside", "ntlmerous": "numerous", "evoltltion": "evolution", "presstlre": "pressure", "otltline": "outline", "opporttlnity": "opportunity", "llattlres": "natures", "cotlrses": "courses", "factllties": "faculties", "freqtlent": "frequent", "incltlded": "included", "ineqtlalities": "inequalities", "trtlly": "truly", "lntlst": "must", "futtlre": "future", "variotls": "various", "reptlblic": "republic", "trtlth": "truth", "gtlard": "guard", "instittltioll": "institutioll", "tntlst": "must", "massachtlsetts": "massachusetts", "trile": "true", "grollp": "group", "ollr": "our", "flllfil": "fulfil", "secllring": "securing", "pllrpose": "purpose", "throllgh": "through", "thlls": "thus", "institlltions": "institutions", "valllable": "valuable", "withollt": "without", "gradllal": "gradual", "allleriean": "ameriean", "llntil": "until", "sllllt": "shut", "ollght": "ought", "featllre": "feature", "statllte": "statute", "prodllced": "produced", "sllcll": "such", "ollrselves": "ourselves", "formlllate": "formulate", "srollld": "sromd", "qllalify": "qualify", "jllst": "just", "reslllts": "results", "sllrely": "surely", "stlldy": "study", "llndertaken": "undertaken", "sllrprised": "surprised", "llnder": "under", "belgillm": "belgium", "eqllally": "equally", "conseqllent": "consequent", "fllll": "full", "wollld": "would", "edlleation": "edueation", "individllals": "individuals", "jllry": "jury", "lllleler": "ulleler", "centllry": "century", "isslles": "issues", "cllrriculum": "curriculum", "sllperiority": "superiority", "colllonercial": "comonercial", "sllggests": "suggests", "illllstratioll": "illustration", "sllffrage": "suffrage", "sllbsequent": "subsequent", "formlllation": "formulation", "careflll": "careful", "fllllctioll": "fmlctioll", "secllrity": "security", "isslle": "issue", "shollld": "should", "llnderlying": "underlying", "sllppose": "suppose", "reprodllction": "reproduction", "sllbjects": "subjects", "eolllltries": "eomltries", "eurriellluln": "eurrieululn", "pictllre": "picture", "accollnt": "account", "sllccess": "success", "ellrope": "europe", "sllldjects": "smdjects", "pllrest": "purest", "yoll": "you", "lnlltual": "mutual", "olltburst": "outburst", "bllsilless": "business", "qllietly": "quietly", "sllccessfully": "successfully", "dlle": "due", "crllel": "cruel", "sllpplies": "supplies", "arduolls": "arduous", "llrged": "urged", "sllitable": "suitable", "statlls": "status", "reglllatioll": "regmatioll", "grollps": "groups", "consciollsly": "consciously", "pllrstlit": "pursuit", "prodllce": "produce", "illstitlltioll": "institution", "purslle": "pursue", "tllrn": "turn", "particlllar": "particular", "successflll": "successful", "sollgllt": "sought", "illtellectllal": "intellectual", "difficlllties": "difficulties", "collseqllently": "consequently", "rllssel": "russel", "reglllator": "regulator", "sllrvive": "survive", "inflllence": "influence", "eclllcatioll": "education", "bllt": "but", "sllollld": "sllomd", "jllrists": "jurists", "argllment": "argument", "llntimely": "untimely", "llpon": "upon", "mllst": "must", "natllre": "nature", "secllred": "secured", "jlldgments": "judgments", "ollt": "out", "fllllest": "fullest", "edllcation": "education", "reqllired": "required", "curricllla": "curricula", "uncollsciollsly": "unconsciously", "strllggle": "struggle", "sollrce": "source", "procllre": "procure", "qllestions": "questions", "illflllellee": "illfluellee", "pllts": "puts", "eurrielllllm": "eurrielllum", "jllstice": "justice", "pursllits": "pursuits", "mllltiplied": "multiplied", "unjllst": "unjust", "trlltlls": "truths", "attlericall": "americall", "comttlerce": "commerce", "adattls": "adams", "altruistll": "altruism", "exatllined": "examined", "tllint": "mint", "claitlls": "claims", "eotlld": "eomd", "chatllpion": "champion", "attetllpts": "attempts", "tllayor": "mayor", "tlllclerstalld": "mlclerstalld", "aclatll": "adam", "socialistll": "socialism", "tllorality": "morality", "cotllpetitioll": "competition", "hotlle": "home", "atll": "am", "cotllplacency": "complacency", "tllein": "mein", "wisdotll": "wisdom", "itllportant": "important", "vvllat": "what", "svllicll": "wllial", "svllatever": "wlntever", "svllere": "where", "svllieh": "whieh", "svllell": "whell", "svlliell": "whieh", "svillillg": "willing", "svithitl": "within", "xvllat": "wuat", "xvitl": "win", "xvllicll": "wnicll", "xvllile": "while", "lloxvever": "however", "xvatcll": "watch", "fratnexvork": "framework", "briclclayer": "briddayer", "cllscllss": "dlsdlss", "reeomnlenclecl": "reeomnlended", "clearcllt": "deardlt", "cllllrcll": "dlllrdl", "clclsse": "ddsse", "inclisticltlal": "indistidtlal", "clifficlllties": "diffidllties", "concltlcle": "condtlde", "clilarclly": "dilardly", "clemancled": "demanded", "acllllirably": "admirably", "sholllcl": "shomd", "funclalllelltal": "fundamelltal", "vlllcler": "vmder", "llnclerlyillg": "llnderlymg", "cloetrille": "doetrme", "bellillcl": "bellmd", "illclividual": "mdividual", "clepartrnellt": "department", "lneclici": "medici", "clepartlnellts": "departments", "ullclerstalld": "mlderstalld", "detnancls": "demands", "clistinet": "distmet", "accorclint": "accordmt", "clirectiolls": "direetiolls", "socallecl": "soealled", "adclressilzg": "addressing", "corresponclilzg": "corresponding", "clictiolzaries": "dictionaries", "clefilaite": "definite", "malacly": "mandy", "relacler": "render", "acljustilag": "adjusting", "clesirability": "desirabhity", "wotllcl": "wothd", "leaclersllip": "leadership", "eclueatioll": "edueatioh", "cliserellt": "disereht", "appellcled": "appehded", "ecllleatioll": "edheatioll", "llolclillg": "holding", "jllclte": "jhdte", "preselltecl": "presehted", "cliville": "divine", "attellcling": "attending", "wiclelled": "widened", "illdepenclellce": "independellce", "inciclelltal": "incidental", "attellcls": "attends", "golclell": "golden", "clrawillg": "drawing", "clistillction": "distinction", "feeclillg": "feeding", "understanclillg": "understanding", "sucldell": "sudden", "iclelltified": "identified", "regarclillg": "regarding", "ullderstallcls": "understands", "illclividuals": "individuals", "bidclillg": "bidding", "clefirled": "defined", "crowcliilg": "crowding", "coilsiclerable": "considerable", "clollbtful": "doubtful", "eclllcating": "educating", "llncloubtedly": "undoubtedly", "reclllced": "reduced", "proclllces": "produces", "illdiviclllal": "individual", "illdllstricll": "industrial", "indtlstricll": "industrial", "fclllziliar": "familiar", "rncltters": "matters", "dalxvinislll": "dalwinism", "hllllclrecrs": "hmldrecrs", "loollllcls": "loomlds", "fleeclolll": "fleedom", "fllnclallleiltal": "fllndameiltal", "zzlillclsilllple": "zzlilldsimple", "cleellleci": "deemeci", "lllecllanistn": "medlanistn", "follllclations": "fomldations", "inelllcled": "inemded", "acljustlllellts": "adjustmellts", "cllllillg": "dmillg", "epoclllllakint": "epodmlakint", "abanclotsllllent": "abandotsmlent", "tllllillld": "tmlimd", "llllllllderless": "mmllderless", "allllollllces": "amlomlces", "eolllllluolity": "eommuolity", "gralllelllx": "gramemx", "collllllercial": "commercial", "llllllger": "mmger", "crilllillal": "crimmal", "recolnlllend": "recommend", "maxillluln": "maximum", "eoznllloll": "eommoll", "cotnlllon": "common", "ecollolllic": "eeollomic", "collllllelcial": "eomlllelcial", "comlllelcial": "eommelcial", "lllentiolaed": "mentioned", "collalllon": "common", "departllleilts": "departmehts", "furtllerlllore": "furthermore", "llollle": "home", "llletllod": "method", "elllillent": "eminent", "allilllal": "animal", "lllovemellts": "movements", "alllell": "amen", "dolllillated": "dominated", "goverlllnellt": "govermnent", "ecollolllics": "economics", "ecollolllist": "economist", "eolllmoll": "eommon", "lllanifestatioll": "manifestation", "instrulllellts": "instruments", "evollltioll": "evomtion", "judglllellts": "judgments", "statelllellt": "statement", "becolllillg": "becoming", "agreelllellt": "agreement", "lllilliollaire": "millionaire", "lllatly": "many", "tllilll": "nlim", "colnlllutlity": "colnmunity", "llulllatlity": "llumanity", "atlilllals": "animals", "comlllllnity": "community", "dartlllollth": "dartmouth", "sllblllit": "submit", "comltloll": "common", "colllltly": "commy", "cclltlact": "camact", "conclltlons": "conamons", "eolltlaclietory": "eolmaaietory", "ftltlclalnelltal": "ftmaalnelltal", "clereloldnlent": "dereloldment", "aclnlinistlatioll": "administlatioll", "nlercllatlt": "merdlatlt", "cllanlpiolls": "dlampiolls", "acllievenlent": "adlievement", "ellclorsenlent": "elldorsement", "anllllal": "ammal", "belgillnl": "belgmm", "lnaxinlum": "maximum", "conlulissiollers": "commissiollers", "eonlulereial": "eommereial", "colnlnunity": "eolmnunity", "colunlunity": "eolumunity", "goverlllzlellt": "goverllmellt", "lzlan": "man", "alzlericall": "americall", "lainlself": "himself", "hunlall": "humah", "llunlber": "humber", "denlallds": "demahds", "colulllon": "columon", "lllal": "mal", "ollteollle": "ollteome", "ellligitelled": "emigitelled", "uleolllers": "uleomers", "accotlllt": "accotmt", "ellliolltelleci": "emiolltelleci", "lselllative": "lsemative", "lllelch": "melch", "altrtlidlll": "altrtlidm", "pllllic": "pmlic", "elllploylnellt": "employlnellt", "sllolllci": "sllomci", "ellliglltened": "emiglltened", "lllelst": "melst", "illtinlately": "intimately", "utcollle": "utcome", "ecollllic": "ecomlic", "colllldetitioll": "comldetitioll", "slllitli": "smitli", "elllargelnellt": "emargelnellt", "oxilllation": "oximation", "illlites": "imites", "pernlallent": "permanent", "brollllt": "bromlt", "tllelllfselxres": "tllemfselxres", "beeollle": "beeome", "ellorlllouslt": "ellormouslt", "lllese": "mese", "eolllparatively": "eomparatively", "lllovelnelltvs": "movelnelltvs", "alllat": "amat", "solzllelllliilc": "solzllemliilc", "ldarlialllents": "ldarliaments", "foullled": "foumed", "halllperillg": "hamperillg", "hulllalwity": "humalwity", "elllployts": "employts", "neiglllor": "neigmor", "oportllllity": "oportmlity", "eoznlllullity": "eoznmullity", "collfornlity": "conformity", "sstelll": "sstem", "prollelll": "prollem", "lllailltellance": "mailltellance", "eolllbi": "eombi", "confollllity": "confomlity", "ecoslolllic": "ecoslomic", "pllllldered": "pmlldered", "milcllless": "milcmess", "colllmtlility": "commtlility", "allllounce": "amlounce", "evervlllele": "evervmele", "collllotatioll": "comlotatioll", "delllad": "demad", "eollllnullity": "eomlnullity", "trllislll": "trllism", "eolnplllsorv": "eolnpmsorv", "ecoololllically": "ecoolomically", "tlllouglt": "tmouglt", "natlll": "natm", "elergylllall": "elergymall", "inoxrelllellt": "inoxremellt", "lllerelr": "merelr", "illllst": "imlst", "cqlllcs": "cqmcs", "tstrclllous": "tstrcmous", "zlllllediate": "zmllediate", "walllen": "wamen", "olalllel": "olamel", "partielllar": "partiemar", "lollls": "loms", "prilllitize": "primitize", "colllxnon": "comxnon", "delllonracy": "demonracy", "econelllist": "econemist", "cielllaild": "ciemaild", "resllltvs": "resmtvs", "goverllllaental": "govermlaental", "coilllllollplace": "coimllollplace", "pllldllc": "pmdllc", "colllllonwealth": "comllonwealth", "lualll": "luam", "dolaolllillated": "dolaomillated", "astiglllatisill": "astigmatisill", "eomlllon": "eommon", "lagglllg": "laggmg", "colllel": "comel", "plolllote": "plomote", "plllsuillg": "pmsuillg", "edmtllld": "edmtmd", "lllollopols": "mollopols", "freedollll": "freedoml", "walllile": "wamile", "flllletioll": "fmletioll", "eolllpetitiool": "eompetitiool", "telegraplll": "telegrapm", "lllanr": "manr", "gorrernllletlt": "gorrernmetlt", "stlllgble": "stmgble", "alllellever": "amellever", "tllllk": "tmlk", "reslllti": "resmti", "llli": "mi", "culricllluin": "culricmuin", "colllpetitio": "competitio", "ellliglltenment": "emiglltenment", "illflllellce": "illfmellce", "loeallll": "loeaml", "iylalllly": "iylamly", "milllleapolis": "mimleapolis", "stholll": "sthom", "balllss": "bamss", "fulnislller": "fulnismer", "ulldelllline": "ulldemline", "nlllolber": "nmolber", "rlllillg": "rmillg", "lllel": "mel", "lllle": "mle", "illllabiteci": "imlabiteci", "llollls": "lloms", "lnerciflll": "lnercifm", "luillillltlln": "luillimtlln", "eolllplete": "eomplete", "governlnelltal": "govermnental", "ullwllolesollle": "ullwllolesome", "illllerent": "imlerent", "ellltivated": "emtivated", "lllerel": "merel", "rollllg": "romlg", "axiolllatic": "axiomatic", "sallltary": "samtary", "colllluercial": "comluercial", "llltrarational": "mtrarational", "furllishes": "fumishes", "rllonarchies": "monarchies", "suprerlle": "supreme", "rlle": "me", "sorlle": "some", "prirllary": "primary", "toucllillg": "toucllmg", "luakillg": "luakmg", "illterlaational": "mterlaational", "cotlisietilla": "cotlisietma", "rellbeillg": "rellbemg", "dllrillg": "dllrmg", "epocllmakillg": "epocllmakmg", "nvisconsill": "nvisconsm", "illissioll": "missioll", "illsllite": "msllite", "mazzilli": "mazzmi", "cjefilli": "cjefmi", "follonvillg": "follonvmg", "traillizag": "tramizag", "accollntillg": "accollntmg", "untilled": "untmed", "illiolaty": "miolaty", "illiport": "miport", "halldillg": "halldmg", "wiscolsill": "wiscolsm", "aaillst": "aamst", "demolills": "demolms", "ravill": "ravm", "cleallillg": "cleallmg", "coillpttitioil": "compttitioil", "eonlpetillg": "eonlpetmg", "illdon": "mdon", "illstallce": "mstallce", "illnovavion": "mnovavion", "aniillalws": "animalws", "illdustria": "mdustria", "lnedicille": "lnedicme", "tillrestlicted": "tmrestlicted", "illapressioll": "mapressioll", "ozigillal": "ozigmal", "becill": "becm", "tusilless": "tusmess", "failly": "famy", "liaxtillc": "liaxtmc", "govelnillelltal": "govelnmelltal", "deterluille": "deterlume", "tllillg": "tllmg", "foliowillg": "foliowmg", "illomilliolls": "momilliolls", "learrlillg": "learrlmg", "illcolplete": "mcolplete", "existillb": "existmb", "begillnillg": "begmnillg", "fillanee": "fmanee", "baraainillg": "baraainmg", "ilillq": "ilmq", "pleparillg": "pleparmg", "proclacillt": "proclacmt", "illd": "md", "illaliellable": "maliellable", "maclliller": "macllmer", "eolgallizillg": "eolgallizmg", "untiljilly": "untiljmy", "colltractillout": "colltractmout", "llerdillg": "llerdmg", "opilliolls": "opmiolls", "killel": "kmel", "illtellsity": "mtellsity", "terlminatillg": "terlminatmg", "illfluellce": "mfluellce", "ridellillb": "ridellmb", "lvuvaill": "lvuvam", "anytllillg": "anytllmg", "illclireet": "mclireet", "accoiillt": "accoimt", "rill": "rm", "onilld": "onmd", "etlailletat": "etlametat", "billeling": "bmeling", "traillino": "tramino", "maellillery": "maellmery", "illtentioll": "mtentioll", "ullclerstalldillg": "ullclerstalldmg", "illstitlltiolls": "mstitlltiolls", "llilldrallee": "llmdrallee", "millimtltll": "mmimtltll", "bookldinclillg": "bookldinclmg", "strellgthenillg": "strellgthenmg", "illdi": "mdi", "systemgivillg": "systemgivmg", "aspililla": "aspilma", "clronvnillg": "clronvnmg", "vasllillg": "vasllmg", "colubillations": "colubmations", "mantlfacturillg": "mantlfacturmg", "nvestlaillstel": "nvestlamstel", "iolcreasillb": "iolcreasmb", "diseiplille": "diseiplme", "accolillts": "accolmts", "illtroductioll": "mtroductioll", "attaillillg": "attamillg", "illasmllcll": "masmllcll", "traiilillg": "traiilmg", "collcernillg": "collcernmg", "inilld": "inmd", "osratifyillg": "osratifymg", "lfotllillg": "lfotllmg", "aeeordill": "aeeordm", "undertalillg": "undertalmg", "illtelligenl": "mtelligenl", "illdividllallv": "mdividllallv", "lielillood": "lielmood", "coollbille": "coollbme", "grontillg": "grontmg", "sneelillg": "sneelmg", "illclustlies": "mclustlies", "notwithstandillt": "notwithstandmt", "eontailled": "eontamed", "opillio": "opmio", "pentlyalillers": "pentlyalmers", "illsufficiellt": "msufficiellt", "eillteellth": "emteellth", "solnetllillt": "solnetllmt", "cultnillating": "cultnmating", "proulotillg": "proulotmg", "llpbrillgillg": "llpbrmgillg", "increasillglv": "increasmglv", "illustl": "mustl", "strvilld": "strvmd", "somethillt": "somethmt", "illtellded": "mtellded", "solnetlaillg": "solnetlamg", "llotllillal": "llotllmal", "illtercotlrse": "mtercotlrse", "sillts": "smts", "illcreasillg": "mcreasillg", "weigllillg": "weigllmg", "opillioil": "opmioil", "stlhetfillg": "stlhetfmg", "precerlillg": "precerlmg", "mallifestillg": "mallifestmg", "attailltxlent": "attamtxlent", "ldrincilles": "ldrincmes", "engilleerillgy": "engmeerillgy", "tillage": "tmage", "illvestlnetlt": "mvestlnetlt", "illottlent": "mottlent", "illstitutiois": "mstitutiois", "htilltxs": "htmtxs", "distilletive": "distmetive", "prillciles": "prmciles", "illdustrra": "mdustrra", "ullceasilltly": "ullceasmtly", "clotllillg": "clotllmg", "bloadenillg": "bloadenmg", "coillproulise": "comproulise", "offsldrillg": "offsldrmg", "plovillg": "plovmg", "cullilillg": "cullilmg", "lililliam": "lilmiam", "elaclillg": "elaclmg", "boolkeepillg": "boolkeepmg", "sometllillz": "sometllmz", "eonstitlltiolls": "eonstimtiolls", "ritllt": "rimt", "llealtll": "llealm", "tlltre": "mtre", "stllgle": "smgle", "outgrowtll": "outgrowm", "tllerebv": "merebv", "collstitllte": "collstimte", "xtvritll": "xtvrim", "olletllocls": "ollemocls", "slrlitlls": "slrlims", "tlltls": "mtls", "ldotll": "ldom", "tllorollghly": "morollghly", "zalitlli": "zalimi", "fllrtller": "fllrmer", "pllilantllropy": "pllilanmropy", "xarotlld": "xaromd", "intelleetllal": "intelleemal", "falltll": "fallm", "tllezn": "mezn", "collstlmtllation": "collstlmmation", "wrlletller": "wrllemer", "vealtll": "vealm", "circutllstallces": "circumstallces", "eentllry": "eenmry", "workswitllotlt": "workswimotlt", "otllernvise": "omernvise", "tllouollt": "mouollt", "walitll": "walim", "vitllin": "vimin", "strengtllells": "strengmells", "tllev": "mev", "strentll": "strenm", "tllrotlgll": "mrotlgll", "tlleoll": "meoll", "strelabtll": "strelabm", "tllexl": "mexl", "celltllries": "cellmries", "tlleologialls": "meologialls", "comptllsioll": "compmsioll", "fllrtllel": "fllrmel", "tllelefole": "melefole", "stllclellts": "smclellts", "goetlles": "goemes", "tllrollth": "mrollth", "tlleself": "meself", "eonstitlltions": "eonstimtions", "tllotlt": "motlt", "laitll": "laim", "tllenllore": "menllore", "altovetller": "altovemer", "ritllout": "rimout", "sstllen": "ssmen", "tllaol": "maol", "laeveltlleless": "laevelmeless", "flortllerlrlore": "flormerlrlore", "stnitll": "stnim", "rtllicll": "rmicll", "allotller": "allomer", "institlltiolas": "instimtiolas", "tlleoly": "meoly", "lnallagetllellt": "lnallagemellt", "tllorllsoll": "morllsoll", "nlitll": "nlim", "tllilagle": "milagle", "collstitlltiollal": "collstimtiollal", "tllz": "mz", "tlldoll": "mdoll", "ritll": "rim", "govertllalellt": "govermalellt", "tlleil": "meil", "dotllinatioll": "dominatioll", "tllotlgllt": "motlgllt", "stllich": "smich", "tllouaht": "mouaht", "ilzstitlltional": "ilzstimtional", "eletllelat": "elemelat", "yolltll": "yollm", "atllotoilt": "amotoilt", "virttll": "virtm", "natlltiplied": "namtiplied", "sylnpatlly": "sylnpamy", "tllre": "mre", "tarentietll": "tarentiem", "bleatlles": "bleames", "slnitlls": "slnims", "otlle": "ome", "togetllel": "togemel", "tllc": "mc", "tllolnas": "molnas", "tllajc": "majc", "otllels": "omels", "otllicll": "omicll", "weitlltiest": "weimtiest", "tllollsands": "mollsands", "cotllci": "comci", "tllrbid": "mrbid", "tllote": "mote", "lotllag": "lomag", "tllellaselves": "mellaselves", "tllroiigh": "mroiigh", "mathenlatllies": "mathenlamies", "autllolity": "aumolity", "slnftll": "slnfm", "cailnibalistll": "cailnibalism", "celatllry": "celamry", "nvitll": "nvim", "entllz": "enmz", "clearness": "deamess", "ourmoclern": "ourmodem", "toclern": "todem", "thestrllggle": "thestmggle", "trllek": "tmek", "rllicll": "micll", "xrllole": "xmole", "strlltgle": "stmtgle", "concerllint": "concemint", "llurllanitarian": "llumanitarian", "strlltrtle": "stmtrtle", "altrllistie": "altmistie", "statesrnall": "statesman", "fllrllishes": "fllmishes", "terllaed": "temaed", "interllationality": "intemationality", "colrlletitiolz": "colmetitiolz", "learlliilg": "leamiilg", "fllrllislles": "fllmislles", "rllo": "mo", "luoderll": "luodem", "aioderll": "aiodem", "fllrllislled": "fllmislled", "strllgle": "stmgle", "wrllat": "wmat", "xvellkllorlln": "xvellkllomn", "instrlletors": "instmetors", "rlleol": "meol", "wrllen": "wmen", "arllicll": "amicll", "seeril": "seem", "rtlarket": "market", "artlollg": "amollg", "jollrnalisln": "journalism", "eolnonullity": "eomonuuity", "lneasllres": "measures", "adjllstlnent": "adjustment", "comlnoll": "commou", "alnotlt": "amout", "colltlacts": "colmacts", "oltlasred": "omasred", "coltlpetilioll": "competilioll", "eoltltior": "eomtior", "aoltl": "aom", "relltlelnen": "relmelnen", "blltland": "blmand", "coaseqelelltly": "coaseqelelmy", "colltl": "colm", "ltlon": "mon", "elilpires": "empires", "adlilires": "admires", "aililnals": "animals", "adalnailt": "adamant", "septelilber": "september", "lrlinor": "minor", "perforlrl": "perform", "lrlonopoly": "monopoly", "coslrlopolitan": "cosmopolitan", "llulnallity": "llumanity", "reselnblallce": "resemblance", "fulldalnental": "fundamental", "lnellt": "ment", "elelnellts": "elements", "lnallaged": "managed", "parlialnellt": "parliament", "sentilnellt": "sentiment", "colntnullity": "community", "improvelnellts": "improvements", "lnelltioned": "mentioned", "colldelnned": "condemned", "elljoylnent": "enjoyment", "lnettlocls": "methods", "wllolesolne": "wholesome", "lnalaifests": "mahifests", "llae": "me", "cleveloplnelat": "development", "collapetitioll": "competition", "olla": "om", "lnealas": "means", "comlnolzs": "commons", "colnpaniolzs": "companions", "ecollolnie": "eeohomie", "eolninereial": "eommereial", "inediuln": "medium", "eolntnon": "eommon", "ulechanisln": "mechanism", "lnolnents": "moments", "govelnlnental": "govemmental", "lninimuln": "minimum", "fllndallnutalilfll": "flmdalmutalilfll", "oovernlnellt": "oovemmellt", "lnenlbel": "membel", "silnplicltwt": "simpliatwt", "llnclertalce": "lmaertalce", "clergylnen": "aergymen", "follnclatioll": "folmaatioll", "lneclieal": "meaieal", "coznnzerce": "commerce", "zllell": "mell", "xrorlzing": "xroming", "algllzzlellt": "algmzlellt", "nalaze": "name", "econzolnic": "ecomomic", "uledixval": "mediwal", "ullicll": "mlidl", "nlull": "mml", "lnulual": "mmual", "colnpetitioul": "competitiom", "currieululn": "curriemum", "eolnpulsion": "eompmsion", "ulaxitnum": "maximum", "ecolloulic": "eeollomic", "wlloul": "whom", "cotntnullity": "comtnuuity", "envirotltnellt": "enviroumellt", "instittltiollssl": "instimtiollssl", "freelottl": "freelom", "struttle": "strume", "instittl": "instim", "walittless": "walimess", "consttlaires": "consmaires", "cleattlres": "cleamres", "opldorttlnities": "opldormnities", "itrlpossible": "impossible", "collcotnitant": "concomitant", "fundatnelltal": "fundamental", "tnucll": "much", "llutnanity": "humanity", "tlaall": "mall", "tlzeorv": "meorv", "internationalistn": "intemationalism", "orfreeclotn": "orfreeaom", "inoclerrl": "moderrl", "cliainetrlcally": "diametrlcally", "altinclanee": "altmdanee", "clisplacine": "displacme", "sclutinized": "sdutmized", "cllartin": "dlartm", "clerines": "dermes", "inclepelldellce": "mdepelldellce", "clltzllinbest": "dltzllmbest", "inclining": "mdining", "clireeting": "direetmg", "beinlling": "beimlmg", "banling": "bammg", "enlarging": "emargmg", "conlflicting": "comflictmg", "rnin": "mm", "selfgoverning": "selfgovemmg", "eolning": "eommg", "lnaintellallee": "mamtellallee", "inaslnuell": "masmuell", "predolninallce": "predommallce", "insulallce": "msmallce", "annoullceinent": "annomlcement", "indulgin": "mdmgin", "tninoletl": "mmoletl", "inereasing": "mereasmg", "intelligeince": "mtelligemce", "intermingled": "mtermmgled", "trainin": "tramm", "collectivisin": "eollectivism", "ilzpartial": "mpartial", "judgilaellt": "judgment", "everilacreasing": "everincreasmg", "irly": "my", "ballkiilg": "ballkmg", "increasilog": "inereasuog", "llearcr": "nearer", "cohlpetitioll": "eohlpetition", "cleally": "eleany", "llcave": "heave", "plzblic": "pnblie", "accordilg": "aeeordilg", "capitalistic": "eapitalistie", "elcconlplish": "eleeonlplish", "commelcial": "eommeleial", "ctlstcxmary": "etlstexmary", "conclusiste": "eonelusiste", "corzlmercial": "eorzlmereial", "collcracts": "colleraets", "condescension": "eondeseension", "contlact": "eontlaet", "clifteretlce": "elifteretlee", "socialilstic": "soeialilstie", "colltractiilg": "eolltraetiilg", "coerciool": "eoereiool", "cozzlmercel": "eozzlmereel", "discloce": "diseloee", "contractingout": "eontraetingout", "cllaslces": "ellaslees", "constricting": "eonstrieting", "commencinb": "eommeneinb", "politicoeeonoulic": "politieoeeonoulie", "procltoctive": "proeltoetive", "noncapitalistic": "noneapitalistie", "beneficence": "benefieenee", "sloccess": "sloeeess", "conduces": "eonduees", "clescriptiosls": "eleseriptiosls", "conttact": "eonttaet", "ccontract": "ceontraet", "signiecance": "signieeanee", "commerclal": "eommerelal", "recollciliatioll": "reeolleiliatioll", "collcract": "colleraet", "clocalilellts": "eloealilellts", "ecolaoonic": "eeolaoonie", "conduce": "eonduee", "dezzlocracy": "dezzloeraey", "contractotlt": "eontraetotlt", "halldelshochschule": "halldelshoehsehule", "coticlitions": "eotielitions", "recluceci": "reclueeei", "econonaic": "eeononaie", "nonscientific": "nonseientifie", "correctives": "eorreetives", "advallceci": "advalleeei", "locical": "loeieal", "econonoic": "eeononoie", "coolcertling": "eooleertling", "collsequelaces": "eollsequelaees", "psycholocically": "psycholoeieally", "aristocracies": "aristoeraeies", "conscientiously": "eonseientiously", "scholasticisln": "seholastieisln", "cllallces": "ellallees", "conclitiols": "eonelitiols", "collcepticall": "colleeptieall", "coontnercial": "eoontnereial", "clescrilde": "eleserilde", "colrect": "eolreet", "selfcleceptioll": "selfeleeeptioll", "corclially": "eorelially", "cotumercial": "eotumereial", "collstrtlctive": "eollstrtletive", "characterj": "eharaeterj", "securityllolclers": "seeurityllolelers", "scocieties": "seoeieties", "acllieveci": "aellieveei", "plutocracy": "plutoeraey", "circumstancesa": "cireumstaneesa", "preponclerance": "preponeleranee", "anarchical": "anarehieal", "accordint": "aeeordint", "collectivism": "eolleetivism", "conceixted": "eoneeixted", "reconciliations": "reeoneiliations", "collsonallce": "eollsonallee", "pgrfectect": "pgrfeeteet", "ecollomlc": "eeollomle", "commerciales": "eommereiales", "colusecratioll": "eoluseeratioll", "lclrce": "lelree", "inlquence": "mlquenee", "predominance": "predommanee", "inlqllence": "mlqllenee", "plinciples": "plmeiples", "stiffeninc": "stiffenme", "colltinlled": "eolltmlled", "continua": "eontmua", "callint": "eallmt", "ceilin": "eeilm", "inrsuence": "mrsuenee", "contriblting": "eontribltmg", "interlaced": "mterlaeed", "contzeinplate": "eontzemplate", "infelicitously": "mfelieitously", "boolkeepinc": "boolkeepme", "productinre": "produetmre", "cinrilization": "emrilization", "comprehending": "eomprehendmg", "princildle": "prmeildle", "directness": "direemess", "cotnmandi": "eommandi", "comtneree": "eommeree", "cotnpetitise": "eompetitise", "dihiculty": "dihiemty", "difiiculty": "difiiemty", "puldlic": "pmdlie", "calefully": "ealefmly", "slloulcr": "sllomer", "peculiarity": "peemiarity", "alullace": "almlaee", "coulage": "eomage", "cultivates": "emtivates", "colulilissioil": "eolmilissioil", "suljects": "smjeets", "coulotry": "eomotry", "woulci": "womei", "uleanc": "meane", "conernzs": "eonerms", "bascoln": "baseom", "elelnelljc": "elemellje", "allilncals": "allimeals", "colnpetitiolo": "eompetitiolo", "lecolne": "leeome", "colnpetitiol": "eompetitiol", "scollolny": "seollomy", "colnollereial": "eomollereial", "eollnected": "eolmeeted", "opporctlnity": "opporetmity", "colilnlissioll": "eolimlissioll", "llncavrorable": "lmeavrorable", "cornwell": "eomwell", "conlests": "eomests", "lseconlitlg": "lseeomitlg", "unclertalze": "undertahe", "lzollaclaries": "holladaries", "einplzyee": "emphyee", "aslzing": "ashmg", "celztzs": "eehtzs", "izlzlications": "izhlieations", "lzatioll": "hation", "llstvvllat": "llstwlnt", "cllalage": "dnlage", "cllalles": "dnlles", "cleoenelatioiz": "deoenentioiz", "gelarcl": "genrd", "awlacle": "awnde", "clezxelaosd": "dezxenosd", "glacluate": "gnduate", "allarclly": "alnrdly", "glacliatols": "gndiatols", "glallclest": "gnlldest", "cllallged": "dnllged", "cllangitlg": "dnngitlg", "pllariseeisrn": "plnriseeism", "ilaovelnellt": "inovemellt", "srellplallned": "srellpnlmed", "lelatilng": "lentimg", "lnerellant": "merelnnt", "wastefullaess": "wastefmness", "ullalienalle": "mnlienalle", "infomlation": "mfomntion", "delating": "dentmg", "ldeginnilags": "ldegmnings", "zzlaking": "zznkmg", "inviolable": "mvionble", "laborpains": "nborpams", "landholding": "nndholdmg", "collstittiollal": "eollstittiolnl", "overcroxtwdilag": "overeroxtwding", "tlansaction": "tnnsaetion", "qllalificatioll": "qlnlifieatioll", "conapetltiola": "eonapetltion", "plactical": "pnetical", "ldeclaration": "ldeenration", "leclared": "leenred", "placad": "pnead", "tlaollc": "tnolle", "fizlance": "fiznnee", "ellaraeteristic": "elnraeteristie", "atlatzzic": "atntzzie", "delatonciatioll": "dentoneiatioll", "aiassaclallsetts": "aiassaenllsetts", "clailelren": "enilelren", "analclar": "analenr", "dictiollarr": "dietiolnrr", "allalces": "alnlees", "colatilauollsly": "eontilauollsly", "bricklayer": "brieknyer", "clailus": "enilus", "pilacy": "piney", "elelaouilced": "elenouileed", "mwallace": "mwalnee", "elabolated": "enbonted", "ilaeqllalities": "ineqlnlities", "enslavilag": "ensnving", "aailalal": "aainnl", "elalartes": "ennrtes", "llatiollal": "lntiolnl", "lessellilag": "lessening", "pursllilag": "pursuing", "wlaell": "when", "tlarougll": "through", "clestitiltioll": "destithtioll", "vilicll": "vhidl", "ilumecliately": "humediately", "cleserwrilig": "deserwrhig", "szilful": "szhfm", "tnigntily": "mignthy", "volltntarily": "vollmtarhy", "goingtile": "gomgthe", "vlpbuilding": "vlpbuhdmg", "upbuilding": "upbuhdmg", "inereasilog": "mereashog", "exprecsioil": "expreesioh", "pectiliarities": "peethiarities", "lilce": "lhee", "collpetitioil": "eollpetitioh", "cilildrell": "ehildrell", "semicivilized": "semieivhized", "cilstdlitalits": "ehstdlitalits", "cnildren": "enhdren", "civili": "eivhi", "jahrbuciler": "jahrbueher", "necessalily": "neeessalhy", "colupetiliol": "eolupethiol", "necessarilwt": "neeessarhwt", "aiiciligan": "aiiehigan", "acquiled": "aequhed", "beilevolellce": "behevolellee", "liilciple": "liheiple", "cotlditioil": "eotlditioh", "ailcr": "aher", "buncile": "bunehe", "fllilctions": "fllhetions", "platitilig": "pntithig", "experililellt": "experhhellt", "tilougllt": "thought", "llpoil": "upoh", "wlliell": "wuieh", "llplleld": "upheld", "llollse": "house", "llollrs": "hours", "brollgllt": "brought", "lligllel": "uighel", "etlougll": "enough", "apprellelld": "apprehend", "llollorable": "honorable", "llatiolls": "natiohs", "cllristiall": "christian", "bellclles": "benches", "cllristiallity": "christianity", "owllersllip": "ownership", "ullderstalld": "uhderstahd", "llotwithstallding": "hotwithstahding", "discllssioll": "dischssioh", "qllotatiolls": "qhotatiohs", "rollssealls": "rohsseahs", "vllcll": "vhch", "envirollmellt": "envirohmeht", "desllitioll": "deshitioh", "coollpesitioll": "coohpesitioh", "llunallitr": "hunahitr", "llppltssioll": "hppltssioh", "llallel": "hahel", "edlleatioll": "edheatioh", "ellvirollinellt": "ellvirohineht", "llstallces": "hstahces", "thlolloll": "thlohoh", "olgallizatioll": "olgahizatioh", "brallelles": "brahehes", "colltellted": "cohtehted", "qllolatioll": "qholatioh", "extellsiolls": "extehsiohs", "llellds": "hehds", "ecollolloies": "ecohohoies", "llotioll": "hotioh", "pllilosopllers": "philosophers", "pllilosoplly": "philosophy", "bradllally": "bradhahy", "llakedlless": "hakedhess", "finalleially": "finaheiahy", "sllffieiellt": "shffieieht", "ellally": "ehahy", "eeolleiliatioll": "eeoheiliatioh", "collstituellts": "cohstituehts", "phellomenoll": "phehomenoh", "inollograplls": "inohographs", "ldllysicialls": "ldhysiciahs", "nallicll": "nahich", "lullell": "luheh", "kllowll": "khowh", "apprellelesioll": "apprehelesioh", "vallixll": "vahixh", "ullquestiolled": "uhquestiohed", "llnqllestionaldly": "hnqhestionaldly", "trallspoltatioll": "trahspoltatioh", "ilnpllgll": "ilnphgh", "attelltioll": "attehtioh", "bellefieellee": "behefieehee", "colltribllte": "cohtribhte", "lellgthelled": "lehgthehed", "ttzollgllt": "ttzohght", "ullioll": "uhioh", "rrolkilgollen": "rrolkhgohen", "llelil": "helh", "philosopllyr": "phhosophyr", "reqlliled": "reqhhed", "alliluals": "ahhuals", "lleilat": "hehat", "eontrolliilg": "eontrohihg", "eompellilag": "eompehhag", "ellsile": "ehshe", "alliluate": "ahhuate", "ilnelltioned": "hnehtioned", "vllile": "vhhe", "llilosophr": "hhosophr", "ellglandn": "ehghndn", "szlall": "szhh", "rebulatioll": "rebuhtioh", "amotlgllunlan": "amotlghunhn", "belzell": "beneh", "bralclles": "bralehes", "sufeciellt": "sufeeieht", "callerl": "eaherl", "reldllblic": "reldhblie", "collstitt": "eohstitt", "havecalled": "haveeahed", "cooteratioll": "eooteratioh", "lcnowll": "lenowh", "gitalltic": "gitahtie", "comptitioll": "eomptitioh", "diametrically": "diametrieahy", "discllssiol": "disehssiol", "approaclleswi": "approaeheswi", "bliclligan": "bliehigan", "percelltate": "pereehtate", "llseci": "hseei", "llcl": "hel", "chanopioll": "ehanopioh", "celltur": "eehtur", "colstrolled": "eolstrohed", "cotoopotofloll": "eotoopotofloh", "clitiolls": "elitiohs", "glorificatioll": "glorifieatioh", "rvllich": "rvhieh", "rhicll": "rhieh", "colldltions": "eohdltions", "llistolical": "histolieal", "reaclli": "reaehi", "lenrellclers": "lenrehelers", "allci": "ahei", "signiecallt": "signieeaht", "llicll": "hiell", "idellce": "idehee", "othicll": "othieh", "clepelldeneiews": "elepehdeneiews", "socalled": "soeahed", "elrcll": "elreh", "wlicll": "wlieh", "educalioll": "eduealioh", "lloic": "hoie", "antecedellts": "anteeedehts", "llowevcjr": "howevejr", "utterallces": "utterahees", "llecessit": "heeessit", "existellces": "existehees", "thllsiastic": "thhsiastie", "mocleroll": "moeleroh", "collse": "eohse", "clisllonorable": "elishonorable", "colupetitioll": "eolupetitioh", "ntagollistic": "ntagohistie", "seeonclly": "seeonehy", "aipearallce": "aipearahee", "libettyvhicll": "libettyvhieh", "wlliclt": "whielt", "recoanitioll": "reeoanitioh", "bxistellce": "bxistehee", "conaproollise": "eonaproohise", "intelleet": "mteheet", "derstallding": "derstahdmg", "allpervading": "ahpervadmg", "disinterestedlless": "dismterestedhess", "parallelint": "parahelmt", "vllinks": "vhmks", "elldeavorint": "ehdeavormt", "intelleetual": "mteheetual", "insellsibly": "msehsibly", "ealling": "eahmg", "eontinlled": "eontmhed", "infolluation": "mfohuation", "teaelling": "teaehmg", "tollegiving": "tohegivmg", "folloving": "fohovmg", "departnellts": "deparmehts", "yeotnall": "yeomah", "eeollotny": "eeohomy", "slloulel": "shomel", "lloul": "hom", "subllulnan": "subhmnan", "mallufaetul": "mahufaetm", "znibllt": "mibht", "srolnell": "sromeh", "eollfornaity": "eohfomaity", "arclently": "ardenhy", "encleavoritlo": "endeavoriho", "llniotls": "lmiohs", "preszntatiotl": "presmtatioh", "trtltn": "trhm", "indtlstlial": "mdhstlial", "instrtletion": "mstrhetion", "atlsinson": "ahsmson", "industlial": "mdushial", "coopetatiotl": "eoopetatioh", "comltitiotl": "eomltitioh", "dtlces": "dhees", "conseqtlentljy": "eonseqhentljy", "plicitly": "plieihy", "imperfectly": "imperfeehy", "coluzetitiotl": "eoluzetitioh", "edtlca": "edhea", "cotupetitiotl": "eotupetitioh", "ecotlomio": "eeohomio", "tljacts": "hjaets", "itleqtlality": "iheqtnlity", "relatlvely": "renhvely", "llaakitlg": "lnakihg", "foutldatioils": "fouhdatiohs", "itldustriallwr": "ihdustriahwr", "tetldelley": "tehdehey", "lldtlstrial": "hdhstrial", "utlqtlestiolled": "uhqtlestiohed", "llotoriotls": "hotoriohs", "sllstaitl": "shstaih", "btlrealls": "bhreahs", "eollsequently": "eohsequenhy", "eollfidently": "eohfidenhy", "stltgestioll": "shtgestioh", "avvorld": "awond", "inarliage": "maniage", "inforl": "mfon", "corltraet": "eontraet", "llowerler": "howener", "perlxrlitted": "penxnitted"}